ssb_tbmd_apis/__init__.py
ssb_tbmd_apis/exports/__init__.py
ssb_tbmd_apis/exports/migrerdok.py
ssb_tbmd_apis/exports/migrermetadb.py
ssb_tbmd_apis/exports/migrervar.py
ssb_tbmd_apis/imports/__init__.py
ssb_tbmd_apis/imports/datadok_meta.py
ssb_tbmd_apis/imports/datadok_open_flatfile.py
ssb_tbmd_apis/imports/dtype_mapping.py
ssb_tbmd_apis/operations/__init__.py
ssb_tbmd_apis/operations/operations_datadok.py
ssb_tbmd_apis/operations/operations_metadb.py
ssb_tbmd_apis/operations/operations_statbank.py
ssb_tbmd_apis/operations/operations_vardok.py
ssb_tbmd_apis/oracle_direct/__init__.py
ssb_tbmd_apis/oracle_direct/oracle_paths.py
ssb_tbmd_apis/paths/__init__.py
ssb_tbmd_apis/paths/linux_stammer.py
ssb_tbmd_apis/paths/try_variations.py
ssb_tbmd_apis/py.typed
ssb_tbmd_apis/tbmd_logger.py
ssb_tbmd_apis/xsds/w3_org_2001_XMLSchema.xsd
ssb_tbmd_apis/xsds/w3_org_2001_xml.xsd
ssb_tbmd_apis/zeep_client.py
ssb_tbmd_apis_python-0.0.2.dist-info/METADATA
ssb_tbmd_apis_python-0.0.2.dist-info/WHEEL
ssb_tbmd_apis_python-0.0.2.dist-info/licenses/LICENSE
ssb_tbmd_apis_python-0.0.2.dist-info/RECORD
