Metadata-Version: 2.4
Name: ssb-tbmd-apis-python
Version: 0.0.2
Summary: SSB Tbmd Apis Python
License-Expression: MIT
License-File: LICENSE
Author: Carl F. Corneil
Author-email: cfc@ssb.no
Requires-Python: >=3.10
Classifier: Development Status :: 4 - Beta
Classifier: Programming Language :: Python :: 3
Classifier: Programming Language :: Python :: 3.10
Classifier: Programming Language :: Python :: 3.11
Classifier: Programming Language :: Python :: 3.12
Classifier: Programming Language :: Python :: 3.13
Classifier: Programming Language :: Python :: 3.14
Requires-Dist: dapla-toolbelt-metadata (>=0.2.5)
Requires-Dist: ipykernel (>=6.29.5)
Requires-Dist: lxml (>=5.3.0)
Requires-Dist: oracledb (>=3.3.0)
Requires-Dist: pandas (>=2.2.3)
Requires-Dist: ssb-fagfunksjoner (>=1.0.6) ; python_version >= "3.10" and python_version < "4.0"
Requires-Dist: zeep (>=4.3.1)
Project-URL: Documentation, https://statisticsnorway.github.io/ssb-tbmd-apis-python
Project-URL: Homepage, https://github.com/statisticsnorway/ssb-tbmd-apis-python
Project-URL: Repository, https://github.com/statisticsnorway/ssb-tbmd-apis-python
